.gitignore
README.rst
bootstrap.py
buildout.cfg
setup.py
collective/__init__.py
collective.portlet.group.egg-info/PKG-INFO
collective.portlet.group.egg-info/SOURCES.txt
collective.portlet.group.egg-info/dependency_links.txt
collective.portlet.group.egg-info/entry_points.txt
collective.portlet.group.egg-info/namespace_packages.txt
collective.portlet.group.egg-info/not-zip-safe
collective.portlet.group.egg-info/requires.txt
collective.portlet.group.egg-info/top_level.txt
collective/portlet/__init__.py
collective/portlet/group/__init__.py
collective/portlet/group/configure.zcml
collective/portlet/group/datatable.pt
collective/portlet/group/groupportlet.pt
collective/portlet/group/groupportlet.py
collective/portlet/group/version.txt
collective/portlet/group/profiles/default/metadata.xml
collective/portlet/group/profiles/default/portlets.xml
collective/portlet/group/tests/__init__.py
collective/portlet/group/tests/base.py
collective/portlet/group/tests/test_portlet.py
docs/HISTORY.txt
docs/INSTALL.txt
docs/LICENSE.GPL
docs/LICENSE.txt