Metadata-Version: 1.0
Name: collective.portlet.group
Version: 1.0
Summary: A portlet to display member of a group
Home-page: https://github.com/collective/collective.portlet.group
Author: JeanMichel FRANCOIS aka toutpt
Author-email: toutpt@gmail.com
License: GPL
Keywords: plone group datatable cyin
Platform: UNKNOWN
Classifier: Framework :: Plone
Classifier: Programming Language :: Python
